sudoisbot/__init__.py
sudoisbot/apis/unifi.py
sudoisbot/apis/weather_pub.py
sudoisbot/common.py
sudoisbot/config.py
sudoisbot/datatypes.py
sudoisbot/listener.py
sudoisbot/network/MDP.py
sudoisbot/network/broker.py
sudoisbot/network/bufferedproxy.py
sudoisbot/network/guide_modified/lpclient.py
sudoisbot/network/guide_modified/ppworker.py
sudoisbot/network/majordomo.py
sudoisbot/network/oldpirate.py
sudoisbot/network/paranoidpirate.py
sudoisbot/network/proxy.py
sudoisbot/network/pub.py
sudoisbot/network/sub.py
sudoisbot/recenttemps.py
sudoisbot/screen/DejaVuSansMono.ttf
sudoisbot/screen/basis33/LICENSE.txt
sudoisbot/screen/basis33/README.txt
sudoisbot/screen/basis33/basis33.ttf
sudoisbot/screen/screen_pub.py
sudoisbot/screen/screen_sub.py
sudoisbot/sendmsg.py
sudoisbot/sendtelegram.py
sudoisbot/sendtelegram_rep.py
sudoisbot/sensors/arduino_current.ino
sudoisbot/sensors/current.py
sudoisbot/sensors/dht.c
sudoisbot/sensors/old.txt
sudoisbot/sensors/rain_pub.py
sudoisbot/sensors/sensors.py
sudoisbot/sensors/temp_pub.py
sudoisbot/sink/graphtemps.py
sudoisbot/sink/models.py
sudoisbot/sink/newdb.py
sudoisbot/sink/notifier.py
sudoisbot/sink/simplestate.py
sudoisbot/sink/sink.py
sudoisbot/tglistener.py
sudoisbot/util/csv2db.py
sudoisbot/util/csv2influx.py
sudoisbot/util/csv2json.py
sudoisbot/util/fromfirstlog.py
sudoisbot/util/json2influx.py
sudoisbot/util/json2mariadb.py
sudoisbot/util/pubtest.py
sudoisbot/util/suball.py
sudoisbot/util/temper_csv_converter.py
sudoisbot/util/updatetemps.sh
sudoisbot-0.3.10.post6.dist-info/entry_points.txt
sudoisbot-0.3.10.post6.dist-info/LICENSE
sudoisbot-0.3.10.post6.dist-info/WHEEL
sudoisbot-0.3.10.post6.dist-info/METADATA
sudoisbot-0.3.10.post6.dist-info/RECORD
